fhir_core/__init__.py
fhir_core/constraints.py
fhir_core/fhirabstractmodel.py
fhir_core/py.typed
fhir_core/types.py
fhir_core/utils.py
fhir_core/xml_utils.py
fhir_core/yaml_utils.py
fhir_core-1.1.3.dist-info/METADATA
fhir_core-1.1.3.dist-info/WHEEL
fhir_core-1.1.3.dist-info/top_level.txt
fhir_core-1.1.3.dist-info/RECORD
